must_tui/__main__.py
must_tui/dialogs.py
must_tui/mib.py
must_tui/must.py
must_tui/must_app.py
must_tui/must_app.tcss
must_tui/data/mib/pcf.dat
must_tui-0.1.2.dist-info/METADATA
must_tui-0.1.2.dist-info/WHEEL
must_tui-0.1.2.dist-info/entry_points.txt
must_tui-0.1.2.dist-info/RECORD
