Metadata-Version: 2.4
Name: must-tui
Version: 0.1.2
Summary: A simple TUI to inspect MUST telemetry and housekeeping.
Author-email: Rik Huygen <rik.huygen@kuleuven.be>
Requires-Python: >=3.12
Requires-Dist: aiofiles>=23.2.1
Requires-Dist: aiohttp>=3.9.0
Requires-Dist: cgse-common>=0.17.3
Requires-Dist: pandas>=2.3.3
Requires-Dist: requests>=2.32.5
Requires-Dist: rich>=14.2.0
Requires-Dist: textual-dev>=1.8.0
Requires-Dist: textual-plot>=0.8.1.post1
Requires-Dist: textual-plotext>=1.0.1
Requires-Dist: textual-timepiece>=0.6.0
Requires-Dist: textual>=6.8.0
Requires-Dist: thefuzz>=0.22.1
Provides-Extra: pcot
Requires-Dist: plato-pcot-scripts; extra == 'pcot'
